textract_parser/__init__.py
textract_parser/__main__.py
textract_parser/textract_parser.py
textract_form_parser-0.1.6.dist-info/LICENSE
textract_form_parser-0.1.6.dist-info/METADATA
textract_form_parser-0.1.6.dist-info/WHEEL
textract_form_parser-0.1.6.dist-info/entry_points.txt
textract_form_parser-0.1.6.dist-info/top_level.txt
textract_form_parser-0.1.6.dist-info/RECORD
